{
  "atomicNumber": 29,
  "symbol": "Cu",
  "name": "Copper",
  "elementCategory": "transition-metal",
  "chemicalBlock": "d",
  "valenceElectrons": 1,
  "oxidationStates": [4, 3, 2, 1],
  "standardUsed": "iupac",
  
  "nist": {
    "atomicMass": 63.546,
    "electronegativity": 1.90,
    "ionizationEnergy": 745.5,
    "atomicRadius": 128,
    "electronAffinity": 118.4,
    "standardMolarEntropy": 33.15,
    "specificHeatCapacity": 0.385,
    "meltingPoint": 1357.77,
    "boilingPoint": 2835,
    "density": 8.96,
    "thermalConductivity": 401,
    "source": "NIST Chemistry WebBook 2024"
  },
  
  "iupac": {
    "atomicMass": 63.546,
    "electronegativity": 1.90,
    "ionizationEnergy": 745.5,
    "atomicRadius": 128,
    "electronAffinity": 118.4,
    "standardMolarEntropy": 33.15,
    "specificHeatCapacity": 0.385,
    "meltingPoint": 1357.77,
    "boilingPoint": 2835,
    "density": 8.96,
    "thermalConductivity": 401,
    "source": "IUPAC Periodic Table 2024"
  },
  
  "physicalProperties": {
    "phase": "solid",
    "appearance": "reddish-metallic",
    "uses": ["electrical wiring", "plumbing", "coins", "electronics", "antimicrobial surfaces"],
    "notes": "Excellent electrical and thermal conductor; essential trace element for life; forms green patina (copper carbonate) when oxidized; used since ancient times"
  },
  
  "lastUpdated": "2026-01-27"
}
